CHANGELOG.txt
LICENCE.txt
MANIFEST.in
README.txt
setup.py
crazy/README.txt
crazy/crazyinvite.py
crazyinvite.egg-info/PKG-INFO
crazyinvite.egg-info/SOURCES.txt
crazyinvite.egg-info/dependency_links.txt
crazyinvite.egg-info/top_level.txt